energy_fault_detector/ABOUT
energy_fault_detector/VERSION
energy_fault_detector/__init__.py
energy_fault_detector/_logs.py
energy_fault_detector/base_config.yaml
energy_fault_detector/c2c_options.yaml
energy_fault_detector/fault_detector.py
energy_fault_detector/logging.yaml
energy_fault_detector/main.py
energy_fault_detector/registration.py
energy_fault_detector/anomaly_scores/__init__.py
energy_fault_detector/anomaly_scores/mahalanobis_score.py
energy_fault_detector/anomaly_scores/rmse_score.py
energy_fault_detector/autoencoders/__init__.py
energy_fault_detector/autoencoders/conditional_autoencoder.py
energy_fault_detector/autoencoders/multilayer_autoencoder.py
energy_fault_detector/config/__init__.py
energy_fault_detector/config/base_config.py
energy_fault_detector/config/config.py
energy_fault_detector/core/__init__.py
energy_fault_detector/core/anomaly_score.py
energy_fault_detector/core/autoencoder.py
energy_fault_detector/core/data_transformer.py
energy_fault_detector/core/fault_detection_model.py
energy_fault_detector/core/fault_detection_result.py
energy_fault_detector/core/model_factory.py
energy_fault_detector/core/save_load_mixin.py
energy_fault_detector/core/threshold_selector.py
energy_fault_detector/data_preprocessing/__init__.py
energy_fault_detector/data_preprocessing/angle_transformer.py
energy_fault_detector/data_preprocessing/column_selector.py
energy_fault_detector/data_preprocessing/data_clipper.py
energy_fault_detector/data_preprocessing/data_preprocessor.py
energy_fault_detector/data_preprocessing/duplicate_value_to_nan.py
energy_fault_detector/data_preprocessing/low_unique_value_filter.py
energy_fault_detector/data_splitting/__init__.py
energy_fault_detector/data_splitting/data_splitter.py
energy_fault_detector/evaluation/__init__.py
energy_fault_detector/evaluation/care2compare.py
energy_fault_detector/evaluation/care_score.py
energy_fault_detector/quick_fault_detection/__init__.py
energy_fault_detector-0.3.0.dist-info/licenses/LICENSE
energy_fault_detector-0.3.0.dist-info/METADATA
energy_fault_detector-0.3.0.dist-info/WHEEL
energy_fault_detector-0.3.0.dist-info/entry_points.txt
energy_fault_detector-0.3.0.dist-info/top_level.txt
energy_fault_detector-0.3.0.dist-info/RECORD
