Metadata-Version: 2.4
Name: energy-fault-detector
Version: 0.3.0
Summary: Automated fault detection in renewable energy assets and power grids.
Author-email: AEFDI <aefdi@iee.fraunhofer.de>
License: Copyright 2025, Fraunhofer Institute for Energy Economics and Energy System Technology (IEE), Kassel
Project-URL: repository, https://github.com/AEFDI/EnergyFaultDetector
Project-URL: documentation, https://aefdi.github.io/EnergyFaultDetector/
Classifier: Development Status :: 4 - Beta
Classifier: Programming Language :: Python :: 3
Classifier: Programming Language :: Python :: 3.9
Classifier: Programming Language :: Python :: 3.10
Classifier: Programming Language :: Python :: 3.11
Classifier: Operating System :: OS Independent
Classifier: License :: OSI Approved :: MIT License
Requires-Python: <3.12,>=3.9
License-File: LICENSE
Requires-Dist: numpy<=1.26.4,>=1.23.5
Requires-Dist: scipy<1.17,>=1.11
Requires-Dist: tensorflow==2.15.1
Requires-Dist: pyyaml
Requires-Dist: scikit-learn<=1.7.0,>=1.5.2
Requires-Dist: pandas>=2.0
Requires-Dist: cerberus
Requires-Dist: matplotlib>=3.9.0
Requires-Dist: optuna>=4.0
Requires-Dist: chardet>=5.0
Requires-Dist: requests~=2.32.4
Provides-Extra: docs
Requires-Dist: sphinx; extra == "docs"
Requires-Dist: sphinx-rtd-theme; extra == "docs"
Requires-Dist: sphinx-autodoc-typehints; extra == "docs"
Requires-Dist: sphinx-copybutton; extra == "docs"
Provides-Extra: dev
Requires-Dist: twine; extra == "dev"
Requires-Dist: pylint; extra == "dev"
Requires-Dist: pytest; extra == "dev"
Requires-Dist: pytest-cov; extra == "dev"
Requires-Dist: build; extra == "dev"
Dynamic: license-file
Dynamic: provides-extra
Dynamic: requires-dist
